{
    "coord": {
        "lon": -47.5253,
        "lat": -18.7235
    },
    "weather": [
        {
            "id": 803,
            "main": "Clouds",
            "description": "broken clouds",
            "icon": "04n"
        }
    ],
    "base": "stations",
    "main": {
        "temp": 25.83,
        "feels_like": 25.3,
        "temp_min": 25.83,
        "temp_max": 25.83,
        "pressure": 1013,
        "humidity": 32,
        "sea_level": 1013,
        "grnd_level": 913
    },
    "visibility": 10000,
    "wind": {
        "speed": 2.17,
        "deg": 151,
        "gust": 2.21
    },
    "clouds": {
        "all": 74
    },
    "dt": 1758067198,
    "sys": {
        "country": "BR",
        "sunrise": 1758013495,
        "sunset": 1758056705
    },
    "timezone": -10800,
    "id": 3456848,
    "name": "Monte Carmelo",
    "cod": 200
}