{
    "coord": {
        "lon": -47.5253,
        "lat": -18.7235
    },
    "weather": [
        {
            "id": 804,
            "main": "Clouds",
            "description": "overcast clouds",
            "icon": "04d"
        }
    ],
    "base": "stations",
    "main": {
        "temp": 20.9,
        "feels_like": 21.29,
        "temp_min": 20.9,
        "temp_max": 20.9,
        "pressure": 1016,
        "humidity": 86,
        "sea_level": 1016,
        "grnd_level": 915
    },
    "visibility": 10000,
    "wind": {
        "speed": 3.67,
        "deg": 6,
        "gust": 5.33
    },
    "clouds": {
        "all": 100
    },
    "dt": 1762179307,
    "sys": {
        "country": "BR",
        "sunrise": 1762158534,
        "sunset": 1762204701
    },
    "timezone": -10800,
    "id": 3456848,
    "name": "Monte Carmelo",
    "cod": 200
}