{
    "coord": {
        "lon": -47.5253,
        "lat": -18.7235
    },
    "weather": [
        {
            "id": 801,
            "main": "Clouds",
            "description": "few clouds",
            "icon": "02d"
        }
    ],
    "base": "stations",
    "main": {
        "temp": 29.44,
        "feels_like": 28.69,
        "temp_min": 29.44,
        "temp_max": 29.44,
        "pressure": 1012,
        "humidity": 36,
        "sea_level": 1012,
        "grnd_level": 913
    },
    "visibility": 10000,
    "wind": {
        "speed": 5.66,
        "deg": 328,
        "gust": 8.67
    },
    "clouds": {
        "all": 14
    },
    "dt": 1758546983,
    "sys": {
        "country": "BR",
        "sunrise": 1758531573,
        "sunset": 1758575162
    },
    "timezone": -10800,
    "id": 3456848,
    "name": "Monte Carmelo",
    "cod": 200
}