{
    "coord": {
        "lon": -47.5253,
        "lat": -18.7235
    },
    "weather": [
        {
            "id": 803,
            "main": "Clouds",
            "description": "broken clouds",
            "icon": "04d"
        }
    ],
    "base": "stations",
    "main": {
        "temp": 25.31,
        "feels_like": 25.25,
        "temp_min": 25.31,
        "temp_max": 25.31,
        "pressure": 1008,
        "humidity": 52,
        "sea_level": 1008,
        "grnd_level": 909
    },
    "visibility": 10000,
    "wind": {
        "speed": 3.71,
        "deg": 331,
        "gust": 6.82
    },
    "clouds": {
        "all": 68
    },
    "dt": 1764095292,
    "sys": {
        "country": "BR",
        "sunrise": 1764059038,
        "sunset": 1764106244
    },
    "timezone": -10800,
    "id": 3456848,
    "name": "Monte Carmelo",
    "cod": 200
}