{
    "coord": {
        "lon": -47.5253,
        "lat": -18.7235
    },
    "weather": [
        {
            "id": 803,
            "main": "Clouds",
            "description": "broken clouds",
            "icon": "04d"
        }
    ],
    "base": "stations",
    "main": {
        "temp": 31.91,
        "feels_like": 30.31,
        "temp_min": 31.91,
        "temp_max": 31.91,
        "pressure": 1011,
        "humidity": 26,
        "sea_level": 1011,
        "grnd_level": 913
    },
    "visibility": 10000,
    "wind": {
        "speed": 2.56,
        "deg": 29,
        "gust": 2.21
    },
    "clouds": {
        "all": 83
    },
    "dt": 1760119063,
    "sys": {
        "country": "BR",
        "sunrise": 1760085849,
        "sunset": 1760130578
    },
    "timezone": -10800,
    "id": 3456848,
    "name": "Monte Carmelo",
    "cod": 200
}