{
    "coord": {
        "lon": -47.5253,
        "lat": -18.7235
    },
    "weather": [
        {
            "id": 503,
            "main": "Rain",
            "description": "very heavy rain",
            "icon": "10n"
        }
    ],
    "base": "stations",
    "main": {
        "temp": 23.67,
        "feels_like": 24.05,
        "temp_min": 23.67,
        "temp_max": 23.67,
        "pressure": 1010,
        "humidity": 75,
        "sea_level": 1010,
        "grnd_level": 910
    },
    "visibility": 10000,
    "wind": {
        "speed": 0.86,
        "deg": 175,
        "gust": 1.2
    },
    "rain": {
        "1h": 18.94
    },
    "clouds": {
        "all": 83
    },
    "dt": 1762120118,
    "sys": {
        "country": "BR",
        "sunrise": 1762072161,
        "sunset": 1762118272
    },
    "timezone": -10800,
    "id": 3456848,
    "name": "Monte Carmelo",
    "cod": 200
}