{
    "coord": {
        "lon": -47.5253,
        "lat": -18.7235
    },
    "weather": [
        {
            "id": 801,
            "main": "Clouds",
            "description": "few clouds",
            "icon": "02d"
        }
    ],
    "base": "stations",
    "main": {
        "temp": 27.27,
        "feels_like": 28.77,
        "temp_min": 27.27,
        "temp_max": 27.27,
        "pressure": 1010,
        "humidity": 64,
        "sea_level": 1010,
        "grnd_level": 911
    },
    "visibility": 10000,
    "wind": {
        "speed": 2.27,
        "deg": 325,
        "gust": 2.5
    },
    "clouds": {
        "all": 12
    },
    "dt": 1774371112,
    "sys": {
        "country": "BR",
        "sunrise": 1774343686,
        "sunset": 1774387073
    },
    "timezone": -10800,
    "id": 3456848,
    "name": "Monte Carmelo",
    "cod": 200
}