{
    "coord": {
        "lon": -47.5253,
        "lat": -18.7235
    },
    "weather": [
        {
            "id": 803,
            "main": "Clouds",
            "description": "broken clouds",
            "icon": "04d"
        }
    ],
    "base": "stations",
    "main": {
        "temp": 27.64,
        "feels_like": 28.22,
        "temp_min": 27.64,
        "temp_max": 27.64,
        "pressure": 1011,
        "humidity": 52,
        "sea_level": 1011,
        "grnd_level": 912
    },
    "visibility": 10000,
    "wind": {
        "speed": 3.1,
        "deg": 36,
        "gust": 3.7
    },
    "clouds": {
        "all": 77
    },
    "dt": 1766249868,
    "sys": {
        "country": "BR",
        "sunrise": 1766219407,
        "sunset": 1766267126
    },
    "timezone": -10800,
    "id": 3456848,
    "name": "Monte Carmelo",
    "cod": 200
}