{
    "coord": {
        "lon": -47.5253,
        "lat": -18.7235
    },
    "weather": [
        {
            "id": 803,
            "main": "Clouds",
            "description": "broken clouds",
            "icon": "04n"
        }
    ],
    "base": "stations",
    "main": {
        "temp": 20.21,
        "feels_like": 20.09,
        "temp_min": 20.21,
        "temp_max": 20.21,
        "pressure": 1011,
        "humidity": 69,
        "sea_level": 1011,
        "grnd_level": 911
    },
    "visibility": 10000,
    "wind": {
        "speed": 2.65,
        "deg": 119,
        "gust": 5.27
    },
    "clouds": {
        "all": 53
    },
    "dt": 1762501466,
    "sys": {
        "country": "BR",
        "sunrise": 1762504037,
        "sunset": 1762550420
    },
    "timezone": -10800,
    "id": 3456848,
    "name": "Monte Carmelo",
    "cod": 200
}