{
    "coord": {
        "lon": -47.5253,
        "lat": -18.7235
    },
    "weather": [
        {
            "id": 803,
            "main": "Clouds",
            "description": "broken clouds",
            "icon": "04d"
        }
    ],
    "base": "stations",
    "main": {
        "temp": 26.09,
        "feels_like": 26.09,
        "temp_min": 26.09,
        "temp_max": 26.09,
        "pressure": 1012,
        "humidity": 72,
        "sea_level": 1012,
        "grnd_level": 912
    },
    "visibility": 10000,
    "wind": {
        "speed": 1.99,
        "deg": 25,
        "gust": 2.13
    },
    "clouds": {
        "all": 65
    },
    "dt": 1773171672,
    "sys": {
        "country": "BR",
        "sunrise": 1773133887,
        "sunset": 1773178174
    },
    "timezone": -10800,
    "id": 3456848,
    "name": "Monte Carmelo",
    "cod": 200
}