{
    "coord": {
        "lon": -47.5253,
        "lat": -18.7235
    },
    "weather": [
        {
            "id": 804,
            "main": "Clouds",
            "description": "overcast clouds",
            "icon": "04d"
        }
    ],
    "base": "stations",
    "main": {
        "temp": 20.46,
        "feels_like": 20.57,
        "temp_min": 20.46,
        "temp_max": 20.46,
        "pressure": 1017,
        "humidity": 77,
        "sea_level": 1017,
        "grnd_level": 916
    },
    "visibility": 10000,
    "wind": {
        "speed": 1.59,
        "deg": 189,
        "gust": 1.71
    },
    "clouds": {
        "all": 100
    },
    "dt": 1758624721,
    "sys": {
        "country": "BR",
        "sunrise": 1758617919,
        "sunset": 1758661572
    },
    "timezone": -10800,
    "id": 3456848,
    "name": "Monte Carmelo",
    "cod": 200
}