{
    "coord": {
        "lon": -47.5253,
        "lat": -18.7235
    },
    "weather": [
        {
            "id": 801,
            "main": "Clouds",
            "description": "few clouds",
            "icon": "02d"
        }
    ],
    "base": "stations",
    "main": {
        "temp": 25.98,
        "feels_like": 25.98,
        "temp_min": 25.98,
        "temp_max": 25.98,
        "pressure": 1016,
        "humidity": 64,
        "sea_level": 1016,
        "grnd_level": 916
    },
    "visibility": 10000,
    "wind": {
        "speed": 2.71,
        "deg": 3,
        "gust": 3.33
    },
    "clouds": {
        "all": 17
    },
    "dt": 1769356001,
    "sys": {
        "country": "BR",
        "sunrise": 1769331108,
        "sunset": 1769377964
    },
    "timezone": -10800,
    "id": 3456848,
    "name": "Monte Carmelo",
    "cod": 200
}