{
    "coord": {
        "lon": -47.5253,
        "lat": -18.7235
    },
    "weather": [
        {
            "id": 800,
            "main": "Clear",
            "description": "clear sky",
            "icon": "01n"
        }
    ],
    "base": "stations",
    "main": {
        "temp": 23.7,
        "feels_like": 22.88,
        "temp_min": 23.7,
        "temp_max": 23.7,
        "pressure": 1017,
        "humidity": 29,
        "sea_level": 1017,
        "grnd_level": 917
    },
    "visibility": 10000,
    "wind": {
        "speed": 0.9,
        "deg": 52,
        "gust": 1.01
    },
    "clouds": {
        "all": 1
    },
    "dt": 1757201605,
    "sys": {
        "country": "BR",
        "sunrise": 1757150021,
        "sunset": 1757192611
    },
    "timezone": -10800,
    "id": 3456848,
    "name": "Monte Carmelo",
    "cod": 200
}