{
    "coord": {
        "lon": -47.5253,
        "lat": -18.7235
    },
    "weather": [
        {
            "id": 800,
            "main": "Clear",
            "description": "clear sky",
            "icon": "01n"
        }
    ],
    "base": "stations",
    "main": {
        "temp": 19.27,
        "feels_like": 18.69,
        "temp_min": 19.27,
        "temp_max": 19.27,
        "pressure": 1016,
        "humidity": 55,
        "sea_level": 1016,
        "grnd_level": 915
    },
    "visibility": 10000,
    "wind": {
        "speed": 3.62,
        "deg": 112,
        "gust": 9.06
    },
    "clouds": {
        "all": 0
    },
    "dt": 1757835916,
    "sys": {
        "country": "BR",
        "sunrise": 1757840802,
        "sunset": 1757883887
    },
    "timezone": -10800,
    "id": 3456848,
    "name": "Monte Carmelo",
    "cod": 200
}